sutil/__init__.py
sutil/async_http_client.py
sutil/consts.py
sutil/enum_meta.py
sutil/http_client.py
sutil/http_common.py
sutil/singleton_meta.py
sutil/utils.py
sutil-0.0.2.dist-info/DESCRIPTION.rst
sutil-0.0.2.dist-info/METADATA
sutil-0.0.2.dist-info/RECORD
sutil-0.0.2.dist-info/WHEEL
sutil-0.0.2.dist-info/metadata.json
sutil-0.0.2.dist-info/top_level.txt
