Metadata-Version: 2.0
Name: sutil
Version: 0.0.2
Summary: some python utilities
Home-page: https://github.com/shengxc/sutil
Author: sheng_xc
Author-email: sheng_xc@126.com
License: Apache License 2.0
Platform: UNKNOWN
Classifier: Programming Language :: Python :: 3
Classifier: Operating System :: OS Independent
Requires-Dist: aiohttp (>=3.7.3)
Requires-Dist: requests (>=2.24.0)
